GitHook/__init__.py
GitHook/api.py
GitHook/classes.py
GitHook/events.py
GitHook/tests/__init__.py
Python_GitHook-0.1.0.dist-info/LICENSE
Python_GitHook-0.1.0.dist-info/METADATA
Python_GitHook-0.1.0.dist-info/WHEEL
Python_GitHook-0.1.0.dist-info/top_level.txt
Python_GitHook-0.1.0.dist-info/RECORD
