Metadata-Version: 2.1
Name: Python-GitHook
Version: 0.1.0
Summary: Simple professional github webhook manager
Home-page: https://github.com/ashengaurd/githook
Author: Ashenguard
Author-email: Ashenguard@agmdev.xyz
License: MIT License
Platform: UNKNOWN
Classifier: Programming Language :: Python :: 3
Classifier: License :: OSI Approved :: MIT License
Classifier: Development Status :: 5 - Production/Stable
Classifier: Operating System :: OS Independent
Requires-Python: >=3.8
Requires-Dist: flask
Requires-Dist: requests
Requires-Dist: json
